antpy/__init__.py
antpy/collections.py
antpy/inspect.py
antpy/path.py
antpy-0.0.2.dist-info/LICENSE
antpy-0.0.2.dist-info/METADATA
antpy-0.0.2.dist-info/WHEEL
antpy-0.0.2.dist-info/top_level.txt
antpy-0.0.2.dist-info/RECORD
