Metadata-Version: 2.1
Name: antpy
Version: 0.0.2
Summary: My Python extensions
Home-page: https://github.com/IvanAntipov/AntPy
Author: Ivan Antipov
License: UNKNOWN
Platform: UNKNOWN
Classifier: Programming Language :: Python :: 3
Classifier: License :: OSI Approved :: MIT License
Classifier: Operating System :: OS Independent
Requires-Python: >=3.7
License-File: LICENSE
